{
  "episodes": 2,
  "randomization_level": 0.0,
  "mean_episode_reward": -5408.59387559668,
  "mean_reward_per_step": -13.5214846889917,
  "mean_length": 400.0,
  "mean_maintain_max_stable": 0.0,
  "stable_success_rate": 0.0,
  "capture_rate": 0.0,
  "mean_abs_theta": 2.43391512697295,
  "mean_abs_theta_dot": 6.137027311411256,
  "mean_abs_alpha": 2.6830545228193277,
  "mean_abs_alpha_dot": 2.3180198491777384,
  "mean_abs_pwm": 121.35,
  "step": 30000,
  "phase": "nominal",
  "stage_name": "smoke_nominal",
  "training_level": 0.0,
  "eval_randomization_level": 0.0
}